esi_utils_io/__init__.py
esi_utils_io/cmd.py
esi_utils_io/container.py
esi_utils_io/smcontainers.py
esi_utils_io/bin/__init__.py
esi_utils_io/bin/repotag.py
esi_utils_io-1.1.1.dist-info/licenses/LICENSE.md
esi_utils_io-1.1.1.dist-info/METADATA
esi_utils_io-1.1.1.dist-info/WHEEL
esi_utils_io-1.1.1.dist-info/entry_points.txt
esi_utils_io-1.1.1.dist-info/top_level.txt
esi_utils_io-1.1.1.dist-info/RECORD
