Metadata-Version: 2.4
Name: esi-utils-io
Version: 1.1.1
Summary: USGS Earthquake Impact Utilities for IO
Author-email: Mike Hearne <mhearne@usgs.gov>
License: License
Keywords: utilities,io
Requires-Python: >=3.8
License-File: LICENSE.md
Requires-Dist: numpy>=1.26
Requires-Dist: h5py>=3.1.0
Requires-Dist: pandas>=1.0
Requires-Dist: pytz>=2021.3
Provides-Extra: dev
Requires-Dist: build>=0.7.0; extra == "dev"
Requires-Dist: black>=21; extra == "dev"
Requires-Dist: flake8>=3.9; extra == "dev"
Requires-Dist: ipython>=7.26; extra == "dev"
Requires-Dist: twine>=4.0.2; extra == "dev"
Provides-Extra: test
Requires-Dist: pytest>=6.2; extra == "test"
Provides-Extra: build
Requires-Dist: build; extra == "build"
Requires-Dist: twine; extra == "build"
Requires-Dist: check-wheel-contents; extra == "build"
Dynamic: license-file
